{
  "project_info": {
    "project_number": "144500593534",
    "firebase_url": "https://insta-clone-3dc4f-default-rtdb.europe-west1.firebasedatabase.app",
    "project_id": "insta-clone-3dc4f",
    "storage_bucket": "insta-clone-3dc4f.appspot.com"
  },
  "client": [
    {
      "client_info": {
        "mobilesdk_app_id": "1:144500593534:android:c7dd9526fc0e417b9c992f",
        "android_client_info": {
          "package_name": "com.example.finle_project"
        }
      },
      "oauth_client": [
        {
          "client_id": "144500593534-3l36rh0u156co316e9tlao301fi1jk28.apps.googleusercontent.com",
          "client_type": 3
        }
      ],
      "api_key": [
        {
          "current_key": "AIzaSyAd4Eryrq71A_vok9lsXR0jn2d_orH9R_4"
        }
      ],
      "services": {
        "appinvite_service": {
          "other_platform_oauth_client": [
            {
              "client_id": "144500593534-3l36rh0u156co316e9tlao301fi1jk28.apps.googleusercontent.com",
              "client_type": 3
            }
          ]
        }
      }
    }
  ],
  "configuration_version": "1"
}